ghpages/__init__.py
ghpages/__main__.py
ghpages/main.py
ghpages-0.0.1.dist-info/entry_points.txt
ghpages-0.0.1.dist-info/WHEEL
ghpages-0.0.1.dist-info/METADATA
ghpages-0.0.1.dist-info/RECORD
