Metadata-Version: 2.1
Name: ghpages
Version: 0.0.1
Summary: Publish files to a gh-pages branch on GitHub
License: MIT
Author: Your Name
Author-email: you@example.com
Requires-Python: >=3.7,<4.0
Classifier: License :: OSI Approved :: MIT License
Classifier: Programming Language :: Python :: 3
Classifier: Programming Language :: Python :: 3.7
Classifier: Programming Language :: Python :: 3.8
Classifier: Programming Language :: Python :: 3.9
Classifier: Programming Language :: Python :: 3.10
Requires-Dist: pycommando (>=2.1.3,<3.0.0)
